README.txt
setup.cfg
setup.py
my/__init__.py
my.demo.recipe.egg-info/PKG-INFO
my.demo.recipe.egg-info/SOURCES.txt
my.demo.recipe.egg-info/dependency_links.txt
my.demo.recipe.egg-info/entry_points.txt
my.demo.recipe.egg-info/namespace_packages.txt
my.demo.recipe.egg-info/not-zip-safe
my.demo.recipe.egg-info/requires.txt
my.demo.recipe.egg-info/top_level.txt
my/demo/__init__.py
my/demo/recipe/__init__.py
my/demo/recipe/tests/__init__.py
my/demo/recipe/tests/test_docs.py