Metadata-Version: 1.0
Name: my.demo.recipe
Version: 1.0dev
Summary: a demo recipe for oscon
Home-page: http://ziade.org
Author: Tarek
Author-email: tarek@ziade.org
License: ZPL
Keywords: demo buildout
Platform: UNKNOWN
Classifier: Framework :: Buildout
Classifier: Intended Audience :: Developers
Classifier: Topic :: Software Development :: Build Tools
Classifier: Topic :: Software Development :: Libraries :: Python Modules
Classifier: License :: OSI Approved :: Zope Public License
